webservicex_converttemp/__init__.py
webservicex_converttemp/convert_temperature.py
webservicex_converttemp/tests.py
webservicex_converttemp/version.py
webservicex_converttemp-0.2.0.dist-info/DESCRIPTION.rst
webservicex_converttemp-0.2.0.dist-info/METADATA
webservicex_converttemp-0.2.0.dist-info/RECORD
webservicex_converttemp-0.2.0.dist-info/WHEEL
webservicex_converttemp-0.2.0.dist-info/metadata.json
webservicex_converttemp-0.2.0.dist-info/top_level.txt
