Metadata-Version: 2.0
Name: webservicex-converttemp
Version: 0.2.0
Summary: A Python client for the WebserviceX.NET Temperature UnitConverter webservice.
Home-page: https://github.com/Yobota/WebserviceX-ConvertTemp
Author: Yobota
Author-email: daniel@yobota.xyz
License: MIT
Keywords: temperature conversion webservice client
Platform: UNKNOWN
Classifier: Development Status :: 4 - Beta
Classifier: Intended Audience :: Developers
Classifier: Intended Audience :: Science/Research
Classifier: Topic :: Scientific/Engineering :: Physics
Classifier: Topic :: Software Development :: Libraries :: Python Modules
Classifier: Topic :: Internet :: WWW/HTTP :: Dynamic Content
Classifier: License :: OSI Approved :: MIT License
Classifier: Programming Language :: Python :: 3
Classifier: Programming Language :: Python :: 3.5
Requires-Dist: zeep (>=1.0.0)
